[
  {
    "id": "2a7422cd-1ddf-4cdf-b00d-11f6aa07e0c4",
    "name": "console--005--1.2x4 1",
    "locked": false,
    "visible": true,
    "transform": {
      "x": 10,
      "y": 0,
      "scale": 1
    },
    "type": "image",
    "imageKey": "console--005--1.2x4",
    "baseRect": {
      "width": 73.4,
      "height": 241.4
    },
    "offset": {
      "x": -10.7,
      "y": -0.7
    }
  },
  {
    "id": "00f6b032-b773-4ea7-98c3-51ec589e509d",
    "name": "Rect 1",
    "locked": false,
    "visible": true,
    "transform": {
      "x": 60,
      "y": -120,
      "dx": 0,
      "dy": 0,
      "scale": 1
    },
    "type": "rect",
    "baseRect": {
      "width": 60,
      "height": 60
    }
  }
]